libpyusdt.cpython-312-aarch64-linux-gnu.so
pyusdt-0.1.1.dist-info/WHEEL
pyusdt-0.1.1.dist-info/RECORD
pyusdt-0.1.1.dist-info/top_level.txt
pyusdt-0.1.1.dist-info/METADATA
pyusdt-0.1.1.dist-info/licenses/LICENSE
pyusdt/__init__.py
pyusdt/__main__.py
