Metadata-Version: 2.4
Name: pyusdt
Version: 0.1.1
Summary: Python profiler using USDT probes for low-overhead performance monitoring with bpftrace
Author: Nathan Scott
License-Expression: Apache-2.0
Project-URL: Homepage, https://github.com/natoscott/pyusdt
Project-URL: Repository, https://github.com/natoscott/pyusdt
Project-URL: Issues, https://github.com/natoscott/pyusdt/issues
Keywords: profiling,tracing,usdt,bpftrace,ebpf,monitoring
Classifier: Development Status :: 4 - Beta
Classifier: Intended Audience :: Developers
Classifier: Operating System :: POSIX :: Linux
Classifier: Programming Language :: Python :: 3
Classifier: Programming Language :: Python :: 3.12
Classifier: Programming Language :: Python :: 3.13
Classifier: Programming Language :: Python :: 3.14
Classifier: Programming Language :: C
Classifier: Topic :: Software Development :: Debuggers
Classifier: Topic :: System :: Monitoring
Requires-Python: >=3.12
License-File: LICENSE
Dynamic: license-file
